{
  "textures": {
    "cracked": {
      "author": "ShrimpSnail, Ewan Howell, & MrBrose",
      "variants": {
        "cracked_left": {},
        "cracked_right": {},
        "cracked_old": {
          "author": "Yanuar Mohendra, MrBrose & ShrimpSnail"
        },
        "cracked_old_pixelated": {
          "name": "Cracked Old (Pixelated)",
          "author": "Yanuar Mohendra & ShrimpSnail"
        }
      }
    },
    "smooth": {
      "author": "Ewan Howell",
      "variants": {
        "smooth_inverted": {
          "name": "Smooth (Inverted Highlight)"
        },
        "smooth_old": {
          "name": "Smooth (Old)"
        },
        "smooth_inverted_old": {
          "name": "Smooth (Old) (Inverted Highlight)"
        }
      }
    },
    "flat_coloured": {
      "author": "TheAnnoying"
    },
    "story_mode": {
      "category": "Story Mode",
      "name": "Story Mode (Season 2)",
      "author": "Yanuar Mohendra, ShrimpSnail, & Ewan Howell",
      "variants": {
        "story_mode1": {
          "name": "Story Mode (Season 1)"
        }
      }
    },
    "mineimator": {
      "name": "Mine-Imator Family",
      "author": "ModelBench & ShrimpSnail"
    },
    "gradient": {
      "author": "Ewan Howell"
    },
    "bevelled_gold": {
      "author": "CL697 & ShrimpSnail"
    },
    "mangrove": {
      "name": "Mangrove (Wild Update)",
      "author": "Narrator2 & TheAnnoying"
    },
    "deep_dark": {
      "name": "Deep Dark (Wild Update)",
      "author": "Banjoei & Shrimpsnail"
    },
    "neon_glow": {
      "category": "Neon",
      "author": "Ewan Howell",
      "variants": {
        "neon": {}
      }
    },
    "fruit": {
      "author": "Ewan Howell & DamienBrittan"
    },
    "bubbles": {
      "author": "oliver.mp3"
    },
    "noise": {
      "author": "oliver.mp3",
      "variants": {
        "grass": {
          "author": "ShrimpSnail & DamienBrittan"
        },
        "grass_side": {
          "author": "Magminer & Ewan Howell"
        },  
        "flowers": {
          "author": "SzyszaDev"
        },
        "podzol": {
          "author": "OliviaTheVampire"
        },
        "mycelium": {
          "author": "OliviaTheVampire"
        },
        "crimson_nylium": {
          "author": "OliviaTheVampire"
        },
        "warped_nylium": {
          "author": "OliviaTheVampire"
        }
      }
    },
    "minecon": {
      "author": "Ewan Howell"
    },
    "classic_cobblestone": {
      "author": "Bold_Muddy"
    },
    "oak_planks": {
      "category": "Planks",
      "author": "TheAnnoying",
      "variants": {
        "spruce_planks": {
          "author": "OliviaTheVampire"
        },
        "birch_planks": {
          "author": "OliviaTheVampire"
        },
        "jungle_planks": {
          "author": "OliviaTheVampire"
        },
        "acacia_planks": {
          "author": "OliviaTheVampire"
        },
        "dark_oak_planks": {
          "author": "OliviaTheVampire"
        },
        "mangrove_planks": {
          "author": "OliviaTheVampire"
        },
        "cherry_planks": {
          "author": "OliviaTheVampire"
        },
        "bamboo_planks": {
          "author": "OliviaTheVampire"
        },
        "crimson_planks": {
          "author": "OliviaTheVampire"
        },
        "warped_planks": {
          "author": "OliviaTheVampire"
        }
      }
    },
    "dunes": {
      "author": "Ewan Howell"
    },
    "bee": {
      "author": "Bold_Muddy & Ewan Howell"
    },
    "inner_shadow": {
      "author": "justwilly"
    },
    "smoked": {
      "author": "justwilly"
    },
    "wavey": {
      "author": "justwilly"
    },
    "smooth_beveled": {
      "author": "justwilly"
    },
    "amethyst": {
      "author": "Bold_Muddy"
    },
    "copper": {
      "author": "Ewan Howell",
      "variants": {
        "oxidised_copper": {},
        "oxidising_copper": {}
      }
    },
    "cake": {
      "category": "Cakes",
      "author": "Magminer",
      "variants": {
        "cake_dark_chocolate": {},
        "cake_dark_chocolate_no_drops": {},
        "cake_dark_chocolate_plain": {},
        "cake_dark_chocolate_plain_no_drops": {},
        "cake_honey": {},
        "cake_honey_no_drops": {},
        "cake_honey_plain": {},
        "cake_honey_plain_no_drops": {},
        "cake_milk_chocolate": {
          "author": "Magminer & OliviaTheVampire"
        },
        "cake_milk_chocolate_no_drops": {
          "author": "Magminer & OliviaTheVampire"
        },
        "cake_milk_chocolate_plain": {
          "author": "Magminer & OliviaTheVampire"
        },
        "cake_milk_chocolate_plain_no_drops": {
          "author": "Magminer & OliviaTheVampire"
        },
        "cake_minecraft": {},
        "cake_minecraft_no_drops": {},
        "cake_minecraft_plain": {},
        "cake_minecraft_plain_no_drops": {},
        "cake_strawberry": {},
        "cake_strawberry_no_drops": {},
        "cake_strawberry_plain": {},
        "cake_strawberry_plain_no_drops": {},
        "cake_vanilla": {
          "author": "Magminer & OliviaTheVampire"
        },
        "cake_vanilla_no_drops": {
          "author": "Magminer & OliviaTheVampire"
        },
        "cake_vanilla_plain": {
          "author": "Magminer & OliviaTheVampire"
        },
        "cake_vanilla_plain_no_drops": {
          "author": "Magminer & OliviaTheVampire"
        },
        "cake_white_chocolate": {
          "author": "Magminer & OliviaTheVampire"
        },
        "cake_white_chocolate_no_drops": {
          "author": "Magminer & OliviaTheVampire"
        },
        "cake_white_chocolate_plain": {
          "author": "Magminer & OliviaTheVampire"
        },
        "cake_white_chocolate_plain_no_drops": {
          "author": "Magminer & OliviaTheVampire"
        }
      }
    },
    "beach": {
      "author": "Ewan Howell",
      "variants": {
        "sand": {
          "author": "Magminer"
        }
      }
    },
    "pixel": {
      "author": "MrBrose"
    },
    "ice": {
      "author": "Feby Kah & Ewan Howell"
    },
    "bricks": {
      "author": "IIAmMaker"
    },
    "fired": {
      "author": "FloideN"
    },
    "midnight": {
      "author": "Ninjaabdullah",
      "variants": {
        "midnight_no_stars": {
          "name": "Midnight (No Stars)"
        }
      }
    },
    "dock": {
      "name": "Sky (Dock)",
      "author": "RyanCR",
      "variants": {
        "dock_clear": {
          "name": "Dock (Clear)"
        }
      }
    },
    "trails_and_tales": {
      "author": "Abe H"
    },
    "blueprint": {
      "author": "WassMan"
    },
    "create": {
      "name": "Create Mod",
      "author": "FeDoT_Dev"
    },
    "diamond": {
      "author": "StevePiglin"
    },
    "honeycomb": {
      "author": "Darius The Baguette"
    },
    "metal": {
      "author": "Ace"
    },
    "shiny_texture": {
      "author": "Chipdo"
    },
    "soul": {
      "author": "oliver.mp3"
    },
    "steel_hardening": {
      "author": "TheSamirMC"
    },
    "ukraine_flag": {
      "author": "ratskui"
    },
    "dirt_pth": {
      "author": "HARYA_"
    },
    "snow_side": {
      "author": "HARYA_"
    },
    "starry_night": {
      "author": "HARYA_"
    },
    "dungeons_terracotta": {
      "author": "HARYA_"
    },
    "pride": {
      "author": "Snuzzle",
      "variants": {
        "aroace": {},
        "aromantic": {},
        "asexual": {},
        "bisexual": {},
        "enby": {},
        "fluid": {},
        "gay": {},
        "intersex": {},
        "lesbian": {},
        "trans": {}
    },
    "norway_flag": {
      "author": "OliviaTheVampire"
    },
    "candy_cane": {
      "category": "Candy Canes",
      "author": "OliviaTheVampire",
      "variants": {
        "candy_cane_green": {},
        "candy_cane_pink": {},
        "candy_cane_yellow": {}
      }
    },
    "thing": {
      "author": "OliviaTheVampire"
    },
    "bevelled_bubbles": {
      "author": "oliver.mp3 & OliviaTheVampire"
    },
    "bones": {
      "author": "OliviaTheVampire"
    },
    "something1": {
      "category": "Something",
      "author": "OliviaTheVampire",
      "variants": {
        "something2": {},
        "something3": {},
        "something4": {}
      }
    }
  },
  "overlays": {
    "highlights_bottom": {
      "name": "Highlights (Bottom)",
      "author": "Ewan Howell"
    },
    "highlights_top": {
      "name": "Highlights (Top)",
      "author": "Ewan Howell"
    },
    "bevel": {
      "author": "Ewan Howell"
    },
    "cracks": {
      "author": "Ewan Howell"
    },
    "shine": {
      "author": "Ewan Howell"
    },
    "shine_random": {
      "author": "Ewan Howell",
      "name": "Shine (Random)"
    },
    "outline": {
      "author": "Ewan Howell"
    },
    "inset_outline": {
      "author": "Ewan Howell"
    },
    "edge_fade": {
      "author": "Ewan Howell"
    },
    "tiles": {
      "author": "Ewan Howell"
    },
    "bevel_highlight_bottom": {
      "name": "Bevel Highlight (Bottom)",
      "author": "FloideN"
    },
    "bevel_highlight_top": {
      "name": "Bevel Highlight (Top)",
      "author": "FloideN"
    },
    "big_bevel": {
      "name": "Big Bevel",
      "author": "PopitTart"
    },
    "texture_highlight_1": {
      "name": "Texture Highlight (1)",
      "author": "FloideN"
    },
    "texture_highlight_2": {
      "name": "Texture Highlight (2)",
      "author": "FloideN"
    }
  }
}
